lambdata/__init__.py
lambdata/example_module.py
lambdata/helper_functions.py
lambdata_Vgrams05-0.0.1.dist-info/LICENSE
lambdata_Vgrams05-0.0.1.dist-info/METADATA
lambdata_Vgrams05-0.0.1.dist-info/WHEEL
lambdata_Vgrams05-0.0.1.dist-info/top_level.txt
lambdata_Vgrams05-0.0.1.dist-info/RECORD
